[{
		"index": "/home",
		"title": "统计报表",
		"subs": [{
				"index": "/home",
				"title": "首页"
			},
			{
				"index": "/homeFinancialLoan",
				"title": "金融贷款"
			},
			{
				"index": "/homeWeddingPhoto",
				"title": "婚纱摄影"
			}
		]
	},
	{
		"index": "/rights",
		"title": "权限管理",
		"subs": [{
				"index": "/role",
				"title": "角色管理"
			},
			{
				"index": "/account",
				"title": "账号管理"
			},
			{
				"index": "/customerAccount",
				"title": "客户账号"
			}
		]
	},
	{ "index": "/ad", "title": "广告管理" },
	{ "index": "/recommend", "title": "推荐管理" },
	{ "index": "/product", "title": "产品管理" },
	{
		"index": "/applyRecord",
		"title": "申请记录",
		"subs": [{
				"index": "/financialLoan",
				"title": "金融贷款"
			},
			{
				"index": "/weddingPhoto",
				"title": "婚纱摄影"
			}
		]
	},
	{
		"index": "/submitRecord",
		"title": "提交记录",
		"subs": [{
				"index": "/submitCustomer",
				"title": "提交客户"
			},
			{
				"index": "/submitCustomerService",
				"title": "提交客服"
			}
		]
	},
	{ "index": "/message", "title": "消息管理" },
	{ "index": "/suggest", "title": "建议管理" },
	{
		"index": "/activity",
		"title": "活动管理",
		"subs": [{
				"index": "/activityList",
				"title": "活动列表"
			},
			{
				"index": "/activityForm",
				"title": "表单控件"
			},
			{
				"index": "/activityRecord",
				"title": "申请记录"
			}
		]
	},
	{ "index": "/user", "title": "用户管理" },
	{ "index": "/order", "title": "订单管理" },
	{ "index": "/customer", "title": "客户管理" },
	{
		"index": "/sms",
		"title": "短信管理",
		"subs": [{
				"index": "/smsList",
				"title": "短信列表"
			},
			{
				"index": "/smsTemplate",
				"title": "短信模板"
			}
		]
	},
	{ "index": "/workList", "title": "工单管理" },
	{ "index": "/business", "title": "业务管理" },
	{ "index": "/rules", "title": "规则管理" },
	{ "index": "/soundRecord", "title": "录音质检" },
	{
		"index": "/cluemgr",
		"title": "线索管理",
		"subs": [{
				"index": "/clue",
				"title": "线索公海"
			},
			{
				"index": "/myClue",
				"title": "我的线索"
			}
		]
	},
	{ "index": "/customerServiceManagement", "title": "客服管理" },
	{ "index": "/smsRecord", "title": "短信记录" },
	{ "index": "/workHandle", "title": "工单处理" }
]